setup.py
django_flatpages_plus.egg-info/PKG-INFO
django_flatpages_plus.egg-info/SOURCES.txt
django_flatpages_plus.egg-info/dependency_links.txt
django_flatpages_plus.egg-info/top_level.txt
flatpages_plus/__init__.py
flatpages_plus/admin.py
flatpages_plus/forms.py
flatpages_plus/managers.py
flatpages_plus/middleware.py
flatpages_plus/models.py
flatpages_plus/urls.py
flatpages_plus/views.py
flatpages_plus/migrations/0001_initial.py
flatpages_plus/migrations/0002_auto__add_field_flatpage_owner__add_field_flatpage_status.py
flatpages_plus/migrations/0003_auto__add_field_flatpage_name.py
flatpages_plus/migrations/__init__.py
flatpages_plus/templatetags/__init__.py
flatpages_plus/templatetags/flatpages_plus_tags.py