Metadata-Version: 1.0
Name: django-flatpages-plus
Version: 0.1.1
Summary: A more robust FlatPage app for Django.
Home-page: https://github.com/danawoodman/django-flatpages-plus
Author: Dana Woodman
Author-email: dana@danawoodman.com
License: MIT
Platform: UNKNOWN
